{
    "title":  "SSIM Citrix",
    "subTitle":  "Higher is better",
    "series":  [
                   {
                       "serie":  "Citrix",
                       "data":  [
                                    {
                                        "x":  "Average",
                                        "y":  "0.9727"
                                    },
                                    {
                                        "x":  "99th",
                                        "y":  "0.9742"
                                    },
                                    {
                                        "x":  "95th",
                                        "y":  "0.974"
                                    }
                                ]
                   },
                   {
                       "serie":  "Citrix Optimized",
                       "data":  [
                                    {
                                        "x":  "Average",
                                        "y":  "0.99"
                                    },
                                    {
                                        "x":  "99th",
                                        "y":  "0.9907"
                                    },
                                    {
                                        "x":  "95th",
                                        "y":  "0.9902"
                                    }
                                ]
                   }
               ],
    "unit":  ""
}
